askai_cli/__init__.py
askai_cli/cli.py
askai_cli/google_client.py
askai_cli/load_properties.py
askai_cli/log_response.py
askai_cli/openai_client.py
askai_cli-0.0.1.dist-info/METADATA
askai_cli-0.0.1.dist-info/WHEEL
askai_cli-0.0.1.dist-info/entry_points.txt
askai_cli-0.0.1.dist-info/top_level.txt
askai_cli-0.0.1.dist-info/RECORD
